Hacenada-0.1.2.data/scripts/hacenada
hacenada/__init__.py
hacenada/abstract.py
hacenada/compat.py
hacenada/const.py
hacenada/error.py
hacenada/main.py
hacenada/render.py
hacenada/script.py
hacenada/session.py
hacenada/storage.py
hacenada/test/__init__.py
hacenada/test/test_main.py
hacenada/test/test_render.py
hacenada/test/test_script.py
hacenada/test/test_session.py
hacenada/test/test_storage.py
Hacenada-0.1.2.dist-info/LICENSE
Hacenada-0.1.2.dist-info/METADATA
Hacenada-0.1.2.dist-info/WHEEL
Hacenada-0.1.2.dist-info/top_level.txt
Hacenada-0.1.2.dist-info/RECORD
